<?xml version='1.0' encoding='UTF-8'?>
<song xmlns="http://openlyrics.info/namespace/2009/song" version="0.8">
  <properties>
    <titles>
      <title>All hail King Jesus, all hail Emmanuel,</title>
    </titles>
    <authors>
      <author>Dave Moody</author>
    </authors>
  </properties>
  <lyrics>
    <verse name="v1">
      <lines>All hail King Jesus, all hail Emmanuel,<br/>   King of kings, Lord of lords, bright morning star<br/>   And through all eternity I'll sing Your praises,<br/>   And I'll reign with You, throughout eternity.</lines>
    </verse>
  </lyrics>
</song>
