<?xml version='1.0' encoding='UTF-8'?>
<song xmlns="http://openlyrics.info/namespace/2009/song" version="0.8" createdIn="OpenLP 2.4.6" modifiedIn="OpenLP 2.4.6" modifiedDate="2021-01-09T02:52:54">
  <properties>
    <titles>
      <title>Awake O Israel, Put Off Thy Slumber</title>
    </titles>
    <authors>
      <author>Author Unknown</author>
    </authors>
  </properties>
  <lyrics>
    <verse name="v1">
      <lines>O Hallelujah; O Hallelujah; Hallelujah; praise the Lord.<br/>O Hallelujah; O Hallelujah; Hallelujah; praise the Lord.</lines>
    </verse>
    <verse name="v2">
      <lines>Awake O Israel, put off thy slumber,<br/>And the truth shall set you free.<br/>And out of Zion shall come deliverance,<br/>In the year of Jubilee.</lines>
    </verse>
    <verse name="v3">
      <lines>From the furnace, of much affliction,<br/>I have chosen to behold, and for iron<br/>I give thee silver and for brass I give thee gold.</lines>
    </verse>
    <verse name="v4">
      <lines>Thou art my chosen, for I have sought thee.<br/>Thou art graven on my hand.<br/>And I will gather all those that gather,<br/>And we'll come back to our land. </lines>
    </verse>
    <verse name="v5">
      <lines>Oh aleluya! Oh Aleluya! Aleluya gloria a Dios<br/>Oh aleluya! Oh Aleluya! Aleluya gloria a Dios</lines>
    </verse>
    <verse name="v6">
      <lines>Despierta, Oh Israel de tu sueño<br/>La verdad os librará<br/>Del Monte Sión la salvación vendrá <br/>En el año del jubileo</lines>
    </verse>
    <verse name="v7">
      <lines>En el horno de grande aflicción<br/>He aquí, os escogí<br/>En vez de hierro, os daré plata<br/>En vez de bronce, oro os daré.</lines>
    </verse>
    <verse name="v8">
      <lines>Sois mis hijos, os he comprado<br/>Y en mis manos labrados sois<br/>Os juntaré con los redimidos<br/>A la tierra os traeré.</lines>
    </verse>
  </lyrics>
</song>
