<?xml version='1.0' encoding='UTF-8'?>
<song xmlns="http://openlyrics.info/namespace/2009/song" version="0.8">
  <properties>
    <titles>
      <title>Awaken Unto Righteousness</title>
    </titles>
    <authors>
      <author>Whitestone Farms</author>
    </authors>
  </properties>
  <lyrics>
    <verse name="v1">
      <lines>Awaken unto righteousness,<br/>Ye saints of the most High,<br/>Awaken unto righteousness,<br/>For He is drawing nigh.<br/>And cry "Enter in, enter in<br/>To the joy of thy Master,<br/>Enter in, enter in<br/>To life everlasting!</lines>
    </verse>
  </lyrics>
</song>
