<?xml version='1.0' encoding='UTF-8'?>
<song xmlns="http://openlyrics.info/namespace/2009/song" version="0.8">
  <properties>
    <titles>
      <title>Deliver Thyself, O Zion</title>
    </titles>
    <authors>
      <author>Dan Ricciardelli</author>
    </authors>
  </properties>
  <lyrics>
    <verse name="c1">
      <lines>Sing and rejoice, O daughter of Zion:<br/>For, lo, I come,<br/>And I will dwell in the midst of thee,<br/>Saith the Lord.</lines>
    </verse>
    <verse name="v1">
      <lines>Deliver thyself, O Zion,<br/>That dwellest with the daughter of Babylon,<br/>For he that toucheth you <br/>Toucheth the apple of his eye.</lines>
    </verse>
    <verse name="v2">
      <lines>And many nations shall be joined to the Lord<br/>In that day, and shall be my people:<br/>And I will dwell in the midst of thee.</lines>
    </verse>
    <verse name="v3">
      <lines>And the Lord shall inherit Judah<br/>His portion in the holy land,<br/>And shall choose Jerusalem, Jerusalem again.</lines>
    </verse>
    <verse name="v4">
      <lines>Be silent, O all flesh, before the Lord:<br/>For he is raised up<br/>Out of his holy habitation</lines>
    </verse>
  </lyrics>
</song>
