<?xml version='1.0' encoding='UTF-8'?>
<song xmlns="http://openlyrics.info/namespace/2009/song" version="0.8">
  <properties>
    <titles>
      <title>I Found A New Place In The Heavenlies</title>
    </titles>
    <authors>
      <author>Author Unknown</author>
    </authors>
  </properties>
  <lyrics>
    <verse name="v1">
      <lines>I found a new place in the heavenlies,<br/>In Jesus Christ, in Jesus Christ.<br/>I found a new place in the heavenlies,<br/>In Jesus Christ.<br/>A place of peace, a place of rest,<br/>A place of joy and happiness,<br/>I found a new place in the heavenlies,<br/>In Jesus Christ.</lines>
    </verse>
  </lyrics>
</song>
