<?xml version='1.0' encoding='UTF-8'?>
<song xmlns="http://openlyrics.info/namespace/2009/song" version="0.8">
  <properties>
    <titles>
      <title>I'm Trading My Sorrows</title>
    </titles>
    <authors>
      <author>Author Unknown</author>
    </authors>
  </properties>
  <lyrics>
    <verse name="v1">
      <lines>I'm trading my sorrows<br/>I'm trading my shame<br/>I'm laying it down for the joy of the Lord</lines>
    </verse>
    <verse name="v2">
      <lines>I'm trading my sickness<br/>I'm trading my pain<br/>I'm laying it down for the joy of the Lord</lines>
    </verse>
    <verse name="v3">
      <lines>We say yes Lord, yes Lord, yes, yes Lord<br/>Yes Lord, yes Lord, yes, yes Lord<br/>Yes Lord, yes Lord, yes, yes Lord, amen</lines>
    </verse>
    <verse name="v4">
      <lines>You have turned my mourning into dancing<br/>You have turned my sorrow into joy (2x)</lines>
    </verse>
    <verse name="v5">
      <lines>This is how we overcome (4x)</lines>
    </verse>
  </lyrics>
</song>
