<?xml version='1.0' encoding='UTF-8'?>
<song xmlns="http://openlyrics.info/namespace/2009/song" version="0.8">
  <properties>
    <titles>
      <title>It's Amazing What Praising Can Do</title>
    </titles>
    <authors>
      <author>Author Unknown</author>
    </authors>
  </properties>
  <lyrics>
    <verse name="v1">
      <lines>It's amazing what praising can do.<br/>Hallelujah, hallelujah.<br/>It's amazing what praising can do.<br/>Hallelujah.<br/>I don't worry when things go wrong.<br/>Jesus fills my heart with a song.<br/>It's amazing what praising can do.<br/>Hallelujah.</lines>
    </verse>
  </lyrics>
</song>
