<?xml version='1.0' encoding='UTF-8'?>
<song xmlns="http://openlyrics.info/namespace/2009/song" version="0.8">
  <properties>
    <titles>
      <title>Jesus, Just The Mention Of Your Name</title>
    </titles>
    <authors>
      <author>Author Unknown</author>
    </authors>
  </properties>
  <lyrics>
    <verse name="v1">
      <lines>Jesus, just the mention of Your name,<br/>Flowers grow, the desert blooms again.<br/>Like the fire in the winter's cold,<br/>Like the pure and precious gold.<br/>Jesus, just the mention of Your name.</lines>
    </verse>
  </lyrics>
</song>
