<?xml version='1.0' encoding='UTF-8'?>
<song xmlns="http://openlyrics.info/namespace/2009/song" version="0.8">
  <properties>
    <titles>
      <title>Spirit of God Lift me Up</title>
    </titles>
    <authors>
      <author>Jacob Hanneke</author>
    </authors>
  </properties>
  <lyrics>
    <verse name="v1">
      <lines>I can surely see Your holiness<br/>As I look around this place,<br/>With my arms stretched out<br/>To receive Your love,<br/>I can see You on each face.</lines>
    </verse>
    <verse name="v2">
      <lines>Spirit of God, lift me up,<br/>Spirit of God, lift me up,<br/>Fill me again with Your love,<br/>sweet Spirit of God. (x2)<br/></lines>
    </verse>
  </lyrics>
</song>
