<?xml version='1.0' encoding='UTF-8'?>
<song xmlns="http://openlyrics.info/namespace/2009/song" version="0.8" createdIn="OpenLP 2.4.6" modifiedIn="OpenLP 2.4.6" modifiedDate="2021-01-09T02:56:48">
  <properties>
    <titles>
      <title>The Lord Is Building Jerusalem</title>
    </titles>
    <authors>
      <author>Author Unknown</author>
    </authors>
  </properties>
  <lyrics>
    <verse name="v1">
      <lines>The Lord is building Jerusalem<br/>The Lord is building Jerusalem,<br/>Gathering together the outcasts of Israel,<br/>Healing broken hearts, binding up their wounds.<br/>The Lord is building; the Lord is building Jerusalem.</lines>
    </verse>
  </lyrics>
</song>
