<?xml version='1.0' encoding='UTF-8'?>
<song xmlns="http://openlyrics.info/namespace/2009/song" version="0.8" createdIn="OpenLP 2.4.6" modifiedIn="OpenLP 2.4.6" modifiedDate="2021-01-09T02:57:08">
  <properties>
    <titles>
      <title>They're Coming Down, Lord; I'm Pulling Them Down</title>
    </titles>
    <authors>
      <author>Author Unknown</author>
    </authors>
  </properties>
  <lyrics>
    <verse name="v1">
      <lines>They're coming down, Lord; I'm pulling them down.<br/>One by one, Lord, the altars hit the ground.<br/>First by the Spirit, then I will manifest it.<br/>They're coming down, Lord; I'll wear my crown.</lines>
    </verse>
  </lyrics>
</song>
