<?xml version='1.0' encoding='UTF-8'?>
<song xmlns="http://openlyrics.info/namespace/2009/song" version="0.8">
  <properties>
    <titles>
      <title>Thou art worthy</title>
    </titles>
    <authors>
      <author>Author Unknown</author>
    </authors>
  </properties>
  <lyrics>
    <verse name="v1">
      <lines>Thou art worthy, thou art worthy.<br/>Thou art worthy oh Lord<br/>To receive glory, glory and honour,<br/>Glory and honour and power.<br/>For thou has created all things created.<br/>Thou has created all things.<br/>And for thy pleasure they are created.<br/>Thou art worthy, Oh Lord.</lines>
    </verse>
  </lyrics>
</song>
